internet_monitor_webthing/__init__.py
internet_monitor_webthing/app.py
internet_monitor_webthing/connectivity_monitor.py
internet_monitor_webthing/connectivity_monitor_webthing.py
internet_monitor_webthing/internet_multiple_webthing.py
internet_monitor_webthing/speedtest_monitor.py
internet_monitor_webthing/speedtest_monitor_webthing.py
internet_monitor_webthing-1.0.1.dist-info/LICENSE
internet_monitor_webthing-1.0.1.dist-info/METADATA
internet_monitor_webthing-1.0.1.dist-info/WHEEL
internet_monitor_webthing-1.0.1.dist-info/entry_points.txt
internet_monitor_webthing-1.0.1.dist-info/top_level.txt
internet_monitor_webthing-1.0.1.dist-info/RECORD
