Metadata-Version: 2.1
Name: internet-monitor-webthing
Version: 1.0.1
Summary: A web connected local internet speed and connectivity monitor
Home-page: https://github.com/grro/internet_monitor_webthing
Author: Gregor Roth
Author-email: gregor.roth@web.de
License: MIT
Keywords: webthings,home automation,speedtest,connectivity,internet,local,raspberry,pi
Platform: UNKNOWN
Classifier: Programming Language :: Python :: 3
Classifier: License :: OSI Approved :: Apache Software License
Classifier: Operating System :: OS Independent
Classifier: Development Status :: 3 - Alpha
Requires-Dist: webthing (==0.15.0)
Requires-Dist: speedtest-cli (==2.1.3)
Requires-Dist: ipwhois
Requires-Dist: requests
